setup.py
macrolyzer/__init__.py
macrolyzer/day.py
macrolyzer/macrolyzer.py
macrolyzer/week.py
macrolyzer.egg-info/PKG-INFO
macrolyzer.egg-info/SOURCES.txt
macrolyzer.egg-info/dependency_links.txt
macrolyzer.egg-info/not-zip-safe
macrolyzer.egg-info/requires.txt
macrolyzer.egg-info/top_level.txt