Metadata-Version: 1.1
Name: macrolyzer
Version: 0.1.1
Summary: Macronutrient and weight trend analyzer
Home-page: https://github.com/bradgarropy/macrolyzer
Author: Brad Garropy
Author-email: bradgarropy@gmail.com
License: MIT
Platform: UNKNOWN
Classifier: Development Status :: 3 - Alpha
Classifier: Intended Audience :: Developers
Classifier: License :: OSI Approved :: MIT License
Classifier: Natural Language :: English
Classifier: Programming Language :: Python :: 2.7
Classifier: Topic :: Utilities
